tap_applehealth/__init__.py
tap_applehealth/client.py
tap_applehealth/streams.py
tap_applehealth/tap.py
tap_applehealth-0.0.4.dist-info/LICENSE
tap_applehealth-0.0.4.dist-info/METADATA
tap_applehealth-0.0.4.dist-info/WHEEL
tap_applehealth-0.0.4.dist-info/entry_points.txt
tap_applehealth-0.0.4.dist-info/RECORD
