Metadata-Version: 2.1
Name: tap-applehealth
Version: 0.0.4
Summary: `tap-applehealth` is a Singer tap for Apple Health, built with the Meltano Singer SDK.
License: Apache-2.0
Keywords: ELT,AppleHealth
Author: Felippe F. Caso
Requires-Python: >=3.7.1,<3.12
Classifier: License :: OSI Approved :: Apache Software License
Classifier: Programming Language :: Python :: 3
Classifier: Programming Language :: Python :: 3.8
Classifier: Programming Language :: Python :: 3.9
Classifier: Programming Language :: Python :: 3.10
Classifier: Programming Language :: Python :: 3.11
Provides-Extra: s3
Requires-Dist: boto3 (>=1.28.30,<2.0.0)
Requires-Dist: fs-s3fs (>=1.1.1,<2.0.0) ; extra == "s3"
Requires-Dist: lxml (>=4.9.3,<5.0.0)
Requires-Dist: singer-sdk (>=0.31.0,<0.32.0)
